wzy_learn/__init__.py
wzy_learn-0.1.1.dist-info/LICENSE
wzy_learn-0.1.1.dist-info/METADATA
wzy_learn-0.1.1.dist-info/WHEEL
wzy_learn-0.1.1.dist-info/top_level.txt
wzy_learn-0.1.1.dist-info/RECORD
