Metadata-Version: 2.1
Name: wzy-learn
Version: 0.1.1
Summary: Just a demo
Home-page: https://github.com/Dr-WangZhiyuan/wzy_learn
Author: Dr. Zhiyuan Wang
Author-email: wang1399@e.ntu.edu.sg
License: MIT
Platform: UNKNOWN
Classifier: Programming Language :: Python :: 3
Classifier: License :: OSI Approved :: MIT License
License-File: LICENSE
